README.rst
setup.py
noseapp/__init__.py
noseapp/datastructures.py
noseapp/exthook.py
noseapp.egg-info/PKG-INFO
noseapp.egg-info/SOURCES.txt
noseapp.egg-info/dependency_links.txt
noseapp.egg-info/entry_points.txt
noseapp.egg-info/not-zip-safe
noseapp.egg-info/requires.txt
noseapp.egg-info/top_level.txt
noseapp/app/__init__.py
noseapp/app/base.py
noseapp/app/config.py
noseapp/app/context.py
noseapp/case/__init__.py
noseapp/case/base.py
noseapp/case/context.py
noseapp/case/decorators.py
noseapp/case/screenplay.py
noseapp/core/__init__.py
noseapp/core/collector.py
noseapp/core/constants.py
noseapp/core/extensions.py
noseapp/core/factory.py
noseapp/core/loader.py
noseapp/core/program.py
noseapp/core/runner/__init__.py
noseapp/core/runner/base.py
noseapp/core/runner/performers/__init__.py
noseapp/core/runner/performers/gevent.py
noseapp/core/runner/performers/multiprocessing.py
noseapp/core/runner/performers/threading.py
noseapp/core/suite/__init__.py
noseapp/core/suite/base.py
noseapp/core/suite/performers/__init__.py
noseapp/core/suite/performers/gevent.py
noseapp/core/suite/performers/threading.py
noseapp/ext/__init__.py
noseapp/manage/__init__.py
noseapp/manage/__main__.py
noseapp/manage/commands.py
noseapp/manage/funcs.py
noseapp/plugins/__init__.py
noseapp/plugins/base.py
noseapp/plugins/configure.py
noseapp/suite/__init__.py
noseapp/suite/base.py
noseapp/suite/context.py
noseapp/tools/__init__.py
noseapp/tools/output.py
noseapp/utils/__init__.py
noseapp/utils/common.py
noseapp/utils/pyv.py