Metadata-Version: 1.1
Name: noseapp
Version: 2.2.1
Summary: Framework for test development
Home-page: https://github.com/trifonovmixail/noseapp
Author: Mikhail Trifonov
Author-email: mikhail.trifonov@corp.mail.ru
License: GNU LGPL
Keywords: test unittest framework nose application
Platform: any
Classifier: Development Status :: 4 - Beta
Classifier: Intended Audience :: Developers
Classifier: Operating System :: OS Independent
Classifier: Programming Language :: Python
Classifier: Programming Language :: Python :: 2.7
Classifier: Programming Language :: Python :: 3
Classifier: Topic :: Software Development :: Testing
